gbp_webhook_tts-1.0.1.dist-info/METADATA
gbp_webhook_tts-1.0.1.dist-info/WHEEL
gbp_webhook_tts-1.0.1.dist-info/entry_points.txt
gbp_webhook_tts-1.0.1.dist-info/licenses/LICENSE
gbp_webhook_tts/__init__.py
gbp_webhook_tts/handlers.py
gbp_webhook_tts/py.typed
gbp_webhook_tts/templates/__init__.py
gbp_webhook_tts/templates/build_pulled.ssml
gbp_webhook_tts/utils.py
gbp_webhook_tts-1.0.1.dist-info/RECORD
