Metadata-Version: 2.1
Name: gbp-webhook-tts
Version: 1.0.1
Summary: Text-To-Speech gbp-webhook plugin
Author-Email: Albert Hopkins <marduk@letterboxes.org>
License: GPL3+
Project-URL: homepage, https://github.com/enku/gbp-webhook-tts
Project-URL: repository, https://github.com/enku/gbp-webhook-tts
Requires-Python: >=3.12
Requires-Dist: boto3>=1.37.34
Requires-Dist: platformdirs>=4.3.7
Requires-Dist: Jinja2>=3.1.6
